aiai/README.md
aiai/__init__.py
aiai/main.py
aiai/manage.py
aiai/test_main.py
aiai/utils.py
aiai/app/__init__.py
aiai/app/apps.py
aiai/app/models.py
aiai/app/settings.py
aiai/app/tests.py
aiai/app/migrations/0001_initial.py
aiai/app/migrations/__init__.py
aiai/code_analyzer/__init__.py
aiai/code_analyzer/code_analyzer.py
aiai/code_analyzer/data_file_analyzer.py
aiai/code_analyzer/graph.py
aiai/code_analyzer/readme.md
aiai/code_analyzer/parsers/__init__.py
aiai/code_analyzer/parsers/base.py
aiai/code_analyzer/parsers/python.py
aiai/code_analyzer/tests/__init__.py
aiai/code_analyzer/tests/conftest.py
aiai/code_analyzer/tests/prompt_example.py
aiai/code_analyzer/tests/sample_code.py
aiai/code_analyzer/tests/sample_entrypoint.py
aiai/code_analyzer/tests/simple_test.py
aiai/code_analyzer/tests/test_code_analyzer.py
aiai/code_analyzer/tests/test_context_extraction.py
aiai/code_analyzer/tests/test_crewai_analysis.py
aiai/code_analyzer/tests/test_data_file_analyzer.py
aiai/code_analyzer/tests/test_data_file_tracking.py
aiai/code_analyzer/tests/test_project_analysis.py
aiai/code_analyzer/tests/test_save_in_db.py
aiai/examples/__init__.py
aiai/examples/crewai_agent.py
aiai/examples/example_custom_eval.py
aiai/examples/langgraph_agent.py
aiai/examples/openai_agent.py
aiai/examples/config_file_examples/agents.yaml
aiai/examples/crewai_example/README.md
aiai/examples/crewai_example/__init__.py
aiai/examples/crewai_example/crew.py
aiai/examples/crewai_example/entrypoint.py
aiai/examples/crewai_example/people_data.json
aiai/examples/langgraph_example/__init__.py
aiai/examples/langgraph_example/entrypoint.py
aiai/examples/langgraph_example/langgraph_agent.py
aiai/optimizer/__init__.py
aiai/optimizer/contextualizer.py
aiai/optimizer/rule_extractor.py
aiai/optimizer/rule_locator.py
aiai/optimizer/rule_merger.py
aiai/optimizer/tests/__init__.py
aiai/optimizer/tests/test_rule_extractor.py
aiai/optimizer/tests/test_rule_locator.py
aiai/optimizer/tests/test_rule_merger.py
aiai_cli-0.1.13.dist-info/METADATA
aiai_cli-0.1.13.dist-info/WHEEL
aiai_cli-0.1.13.dist-info/entry_points.txt
aiai_cli-0.1.13.dist-info/RECORD
