Metadata-Version: 2.3
Name: aiai-cli
Version: 0.1.13
Summary: Your friendly neighborhood AI agent optimization AI agent
Author-email: Amir Mehr <amir@zenbase.ai>, Cyrus Nouroozi <cyrus@zenbase.ai>
Requires-Python: >=3.11
Requires-Dist: aiolimiter>=1.2.1
Requires-Dist: django-stubs>=5.1.3
Requires-Dist: django>=5.2
Requires-Dist: docetl>=0.2.2
Requires-Dist: instructor>=1.7.9
Requires-Dist: libcst>=1.7.0
Requires-Dist: litellm==1.60.2
Requires-Dist: networkx>=3.4.2
Requires-Dist: openlit
Requires-Dist: pandas>=2.2.3
Requires-Dist: pydantic>=2.11.3
Requires-Dist: pydash>=8.0.5
Requires-Dist: pydot>=3.0.4
Requires-Dist: python-dotenv>=1.1.0
Requires-Dist: scarf-sdk>=0.1.2
Requires-Dist: sorcery>=0.2.2
Requires-Dist: tqdm>=4.67.1
Requires-Dist: tree-sitter-python>=0.23.6
Requires-Dist: tree-sitter>=0.24.0
Requires-Dist: typer>=0.12.5
Provides-Extra: crewai
Requires-Dist: crewai-tools; extra == 'crewai'
Requires-Dist: crewai==0.114.0; extra == 'crewai'
Provides-Extra: langgraph
Requires-Dist: langgraph>=0.3.31; extra == 'langgraph'
